fabric_powershell/Powershell.py
fabric_powershell/scheduledTasks.py
fabric_powershell/version.py
fabric_powershell/Virtualenv.py
fabric_powershell/__init__.py
fabric_powershell-0.1.0.dist-info/DESCRIPTION.rst
fabric_powershell-0.1.0.dist-info/METADATA
fabric_powershell-0.1.0.dist-info/metadata.json
fabric_powershell-0.1.0.dist-info/RECORD
fabric_powershell-0.1.0.dist-info/top_level.txt
fabric_powershell-0.1.0.dist-info/WHEEL
