Metadata-Version: 2.0
Name: fabric-powershell
Version: 0.1.0
Summary: Fabric functions to run Powershell scripts and manipulate remote Windows servers.
Home-page: http://github.com/adamkerz/fabric-powershell
Author: Adam Kerz
Author-email: github@kerz.id.au
License: BSD 3-Clause
Keywords: fabric powershell
Platform: UNKNOWN
Classifier: Development Status :: 4 - Beta
Classifier: Intended Audience :: Developers
Classifier: Natural Language :: English
Classifier: License :: OSI Approved :: BSD License
Classifier: Operating System :: OS Independent
Classifier: Programming Language :: Python
Classifier: Programming Language :: Python :: 2
Classifier: Programming Language :: Python :: 2.7
Classifier: Topic :: Software Development :: Libraries :: Python Modules
Requires-Dist: fabric
